gab_kedro_sagemaker/__init__.py
gab_kedro_sagemaker/cli.py
gab_kedro_sagemaker/cli_functions.py
gab_kedro_sagemaker/client.py
gab_kedro_sagemaker/config.py
gab_kedro_sagemaker/constants.py
gab_kedro_sagemaker/datasets.py
gab_kedro_sagemaker/decorators.py
gab_kedro_sagemaker/docker.py
gab_kedro_sagemaker/generator.py
gab_kedro_sagemaker/runner.py
gab_kedro_sagemaker/utils.py
gab_kedro_sagemaker-0.3.0.dist-info/LICENSE
gab_kedro_sagemaker-0.3.0.dist-info/METADATA
gab_kedro_sagemaker-0.3.0.dist-info/WHEEL
gab_kedro_sagemaker-0.3.0.dist-info/entry_points.txt
gab_kedro_sagemaker-0.3.0.dist-info/RECORD
