Metadata-Version: 2.1
Name: gab-kedro-sagemaker
Version: 0.3.0
Summary: Kedro plugin with AWS SageMaker Pipelines support
Home-page: https://github.com/getindata/kedro-sagemaker
License: Apache-2.0
Keywords: kedro,sagemaker,aws,mlops
Author: Marcin Zabłocki
Author-email: marcin.zablocki@getindata.com
Maintainer: GetInData MLOPS
Maintainer-email: mlops@getindata.com
Requires-Python: >=3.8,<3.11
Classifier: Development Status :: 4 - Beta
Classifier: License :: OSI Approved :: Apache Software License
Classifier: Programming Language :: Python :: 3
Classifier: Programming Language :: Python :: 3.8
Classifier: Programming Language :: Python :: 3.9
Classifier: Programming Language :: Python :: 3.10
Requires-Dist: backoff (>=2.2.1,<3.0.0)
Requires-Dist: cloudpickle (>=2.2.0,<3.0.0)
Requires-Dist: kedro (>=0.18.3)
Requires-Dist: pydantic (>=1.10.2,<2.0.0)
Requires-Dist: s3fs (>=2022.11.0,<2023.0.0)
Requires-Dist: sagemaker (>=2.117.0,<3.0.0)
Requires-Dist: tarsafe (==0.0.4)
Requires-Dist: zstandard (>=0.19.0,<0.20.0)
Project-URL: Documentation, https://kedro-sagemaker.readthedocs.io/
Project-URL: Repository, https://github.com/getindata/kedro-sagemaker
